aws_cloudwatch_logs_url/__init__.py
aws_cloudwatch_logs_url/aws_cloudwatch_logs_url.py
aws_cloudwatch_logs_url-1.0.3.dist-info/LICENSE
aws_cloudwatch_logs_url-1.0.3.dist-info/METADATA
aws_cloudwatch_logs_url-1.0.3.dist-info/WHEEL
aws_cloudwatch_logs_url-1.0.3.dist-info/RECORD
