Metadata-Version: 2.1
Name: aws-cloudwatch-logs-url
Version: 1.0.3
Summary: generate AWS CloudWatch Logs URL
Home-page: https://github.com/sinofseven/aws-cloudwatch-logs-url-python
License: MIT
Author: sinofseven
Author-email: em.s.00001@gmail.com
Requires-Python: >=3.8.12
Classifier: Development Status :: 4 - Beta
Classifier: License :: OSI Approved :: MIT License
Classifier: Programming Language :: Python :: 3
Classifier: Programming Language :: Python :: 3.9
Classifier: Programming Language :: Python :: 3.10
Classifier: Programming Language :: Python :: 3.11
Classifier: Programming Language :: Python :: 3.12
Classifier: Programming Language :: Python :: 3.8
Classifier: Topic :: Utilities
Project-URL: Repository, https://github.com/sinofseven/aws-cloudwatch-logs-url-python
